{
  "$schema": "https://developer.microsoft.com/json-schemas/fabric/item/report/definition/visualContainer/2.5.0/schema.json",
  "name": "7fd544d850bd909c0378",
  "position": {
    "x": 127.30742912816758,
    "y": 235.59779949739749,
    "z": 21000,
    "height": 34.114713216957604,
    "width": 194.81296758104739,
    "tabOrder": 20000
  },
  "visual": {
    "visualType": "textbox",
    "objects": {
      "general": [
        {
          "properties": {
            "paragraphs": [
              {
                "textRuns": [
                  {
                    "value": "Eventos | ",
                    "textStyle": {
                      "fontWeight": "bold",
                      "fontSize": "9pt",
                      "color": "#b3b3b3"
                    }
                  },
                  {
                    "value": "preponderantes",
                    "textStyle": {
                      "fontFamily": "Segoe UI Semibold",
                      "fontSize": "9pt",
                      "color": "#ffffff"
                    }
                  }
                ]
              }
            ]
          }
        }
      ]
    },
    "visualContainerObjects": {
      "background": [
        {
          "properties": {
            "show": {
              "expr": {
                "Literal": {
                  "Value": "false"
                }
              }
            }
          }
        }
      ],
      "title": [
        {
          "properties": {
            "text": {
              "expr": {
                "Literal": {
                  "Value": "'Por Tipo de Operacao'"
                }
              }
            }
          }
        }
      ]
    },
    "drillFilterOtherVisuals": true
  }
}